DESCRIPTION.rst
MANIFEST.in
README.rst
setup.cfg
setup.py
marcopolo/__init__.py
marcopolo/utils/__init__.py
marcopolo/utils/marcodiscover.py
marcopolo/utils/marcoinstallkey.py
marcopolo_shell.egg-info/PKG-INFO
marcopolo_shell.egg-info/SOURCES.txt
marcopolo_shell.egg-info/dependency_links.txt
marcopolo_shell.egg-info/entry_points.txt
marcopolo_shell.egg-info/namespace_packages.txt
marcopolo_shell.egg-info/not-zip-safe
marcopolo_shell.egg-info/requires.txt
marcopolo_shell.egg-info/top_level.txt
usr/local/bin/marcoinstallkey.sh
usr/local/bin/marcoscp.sh
usr/local/bin/marcosshcommand.sh
usr/local/bin/modifypath.sh