Metadata-Version: 1.1
Name: marcopolo-shell
Version: 0.0.3
Summary: A set of useful utilities for MarcoPolo
Home-page: marcopolo.martinarroyo.net
Author: Diego Martín
Author-email: martinarroyo@usal.es
License: MIT
Keywords: marcopolo shell utilities
Platform: UNKNOWN
Classifier: Development Status :: 3 - Alpha
Classifier: Intended Audience :: Developers
Classifier: Intended Audience :: System Administrators
Classifier: Operating System :: POSIX :: Linux
Classifier: Programming Language :: Python :: 2.7
Classifier: Programming Language :: Python :: 3.4
Classifier: Topic :: System :: Networking
Classifier: License :: OSI Approved :: Mozilla Public License 2.0 (MPL 2.0)
Classifier: Natural Language :: English
Provides: marcopolo.utils
